whatsapp_analyzer/__init__.py
whatsapp_analyzer/analysis_utils.py
whatsapp_analyzer/analyzer.py
whatsapp_analyzer/constants.py
whatsapp_analyzer/exceptions.py
whatsapp_analyzer/parser.py
whatsapp_analyzer/pdf_generator.py
whatsapp_analyzer/plot_utils.py
whatsapp_analyzer/run.py
whatsapp_analyzer/utils.py
whatsapp_groupchat_analyzer-1.0.7.dist-info/licenses/LICENSE
whatsapp_groupchat_analyzer-1.0.7.dist-info/METADATA
whatsapp_groupchat_analyzer-1.0.7.dist-info/WHEEL
whatsapp_groupchat_analyzer-1.0.7.dist-info/top_level.txt
whatsapp_groupchat_analyzer-1.0.7.dist-info/RECORD
